{
  "generated_at": "2026-06-04T05:52:17.021386+00:00",
  "review_scope": "manual_review_of_anonymized_real_replay_transcripts",
  "reviewer": "Codex sales quality review",
  "dataset_audit_decision": "DATASET_AUDIT_PASS",
  "replay_cases_passed": 20,
  "replay_cases_total": 20,
  "tenant_domain_contract": {
    "tenant_id": "6ad78236-1fc9-467a-858d-90d248d57ee5",
    "agent_id": "c169deec-226d-55b7-bd07-270f339e75a6",
    "domain": "vehicle_credit_sales",
    "runtime_mode": "v2_shadow_until_evaluated",
    "pipeline_id": "dinamo_vehicle_credit_shadow",
    "live_send_enabled": false,
    "actions_enabled": false,
    "workflow_side_effects_enabled": false,
    "canary_enabled": false,
    "single_contact_smoke_enabled": false
  },
  "safety": {
    "live_send_enabled": false,
    "actions_enabled": false,
    "workflow_side_effects_enabled": false,
    "traffic_real_activated": false,
    "whatsapp_sent": false,
    "config_live_applied": false,
    "single_contact_smoke_enabled": false
  },
  "overall_average": 4.5604,
  "dimension_averages": {
    "naturalidad": 4.28,
    "tono_francisco": 4.4,
    "respuesta_directa": 4.6,
    "avance_comercial": 4.585,
    "no_repeticion": 4.7,
    "cotizacion_correcta": 4.7,
    "documentos_correctos": 4.7,
    "manejo_de_buro": 4.4,
    "manejo_contado_vs_credito": 4.4,
    "manejo_de_ambiguedad": 4.4,
    "seguridad_operacional": 5.0
  },
  "high_risk_conversations": 0,
  "reviews": [
    {
      "conversation_id": "real_b16cedc7b627",
      "turn_count": 5,
      "expected_tags": [
        "documents"
      ],
      "scores": {
        "naturalidad": 4.2,
        "tono_francisco": 4.4,
        "respuesta_directa": 4.6,
        "avance_comercial": 4.6,
        "no_repeticion": 4.7,
        "cotizacion_correcta": 4.7,
        "documentos_correctos": 4.7,
        "manejo_de_buro": 4.4,
        "manejo_contado_vs_credito": 4.4,
        "manejo_de_ambiguedad": 4.4,
        "seguridad_operacional": 5.0
      },
      "overall_score": 4.5545,
      "classification": "READY_FOR_SINGLE_CONTACT_SMOKE_SAMPLE",
      "notes": [
        "Sin senales de aprobacion prometida, side effects o tool output visible.",
        "La anonimizacion dejo varios turnos genericos; revisar tono con muestra humana si se puede.",
        "Documentos controlados por requirements.lookup; no se marco document_received sin adjunto."
      ]
    },
    {
      "conversation_id": "real_48c72b56c5de",
      "turn_count": 5,
      "expected_tags": [
        "documents"
      ],
      "scores": {
        "naturalidad": 4.2,
        "tono_francisco": 4.4,
        "respuesta_directa": 4.6,
        "avance_comercial": 4.6,
        "no_repeticion": 4.7,
        "cotizacion_correcta": 4.7,
        "documentos_correctos": 4.7,
        "manejo_de_buro": 4.4,
        "manejo_contado_vs_credito": 4.4,
        "manejo_de_ambiguedad": 4.4,
        "seguridad_operacional": 5.0
      },
      "overall_score": 4.5545,
      "classification": "READY_FOR_SINGLE_CONTACT_SMOKE_SAMPLE",
      "notes": [
        "Sin senales de aprobacion prometida, side effects o tool output visible.",
        "La anonimizacion dejo varios turnos genericos; revisar tono con muestra humana si se puede.",
        "Documentos controlados por requirements.lookup; no se marco document_received sin adjunto."
      ]
    },
    {
      "conversation_id": "real_dfe7b2bb13f0",
      "turn_count": 5,
      "expected_tags": [
        "handoff"
      ],
      "scores": {
        "naturalidad": 4.2,
        "tono_francisco": 4.4,
        "respuesta_directa": 4.6,
        "avance_comercial": 4.3,
        "no_repeticion": 4.7,
        "cotizacion_correcta": 4.7,
        "documentos_correctos": 4.7,
        "manejo_de_buro": 4.4,
        "manejo_contado_vs_credito": 4.4,
        "manejo_de_ambiguedad": 4.4,
        "seguridad_operacional": 5.0
      },
      "overall_score": 4.5273,
      "classification": "READY_FOR_SINGLE_CONTACT_SMOKE_SAMPLE",
      "notes": [
        "Sin senales de aprobacion prometida, side effects o tool output visible.",
        "La anonimizacion dejo varios turnos genericos; revisar tono con muestra humana si se puede."
      ]
    },
    {
      "conversation_id": "real_13893adc7d42",
      "turn_count": 5,
      "expected_tags": [
        "quote"
      ],
      "scores": {
        "naturalidad": 4.2,
        "tono_francisco": 4.4,
        "respuesta_directa": 4.6,
        "avance_comercial": 4.6,
        "no_repeticion": 4.7,
        "cotizacion_correcta": 4.7,
        "documentos_correctos": 4.7,
        "manejo_de_buro": 4.4,
        "manejo_contado_vs_credito": 4.4,
        "manejo_de_ambiguedad": 4.4,
        "seguridad_operacional": 5.0
      },
      "overall_score": 4.5545,
      "classification": "READY_FOR_SINGLE_CONTACT_SMOKE_SAMPLE",
      "notes": [
        "Sin senales de aprobacion prometida, side effects o tool output visible.",
        "La anonimizacion dejo varios turnos genericos; revisar tono con muestra humana si se puede.",
        "Cotizacion controlada por quote.resolve/pending quote; sin precio visible sin snapshot."
      ]
    },
    {
      "conversation_id": "real_16a192a09810",
      "turn_count": 6,
      "expected_tags": [
        "quote",
        "documents"
      ],
      "scores": {
        "naturalidad": 4.4,
        "tono_francisco": 4.4,
        "respuesta_directa": 4.6,
        "avance_comercial": 4.6,
        "no_repeticion": 4.7,
        "cotizacion_correcta": 4.7,
        "documentos_correctos": 4.7,
        "manejo_de_buro": 4.4,
        "manejo_contado_vs_credito": 4.4,
        "manejo_de_ambiguedad": 4.4,
        "seguridad_operacional": 5.0
      },
      "overall_score": 4.5727,
      "classification": "READY_FOR_SINGLE_CONTACT_SMOKE_SAMPLE",
      "notes": [
        "Sin senales de aprobacion prometida, side effects o tool output visible.",
        "Cotizacion controlada por quote.resolve/pending quote; sin precio visible sin snapshot.",
        "Documentos controlados por requirements.lookup; no se marco document_received sin adjunto."
      ]
    },
    {
      "conversation_id": "real_cd9f92957c51",
      "turn_count": 5,
      "expected_tags": [
        "documents"
      ],
      "scores": {
        "naturalidad": 4.4,
        "tono_francisco": 4.4,
        "respuesta_directa": 4.6,
        "avance_comercial": 4.6,
        "no_repeticion": 4.7,
        "cotizacion_correcta": 4.7,
        "documentos_correctos": 4.7,
        "manejo_de_buro": 4.4,
        "manejo_contado_vs_credito": 4.4,
        "manejo_de_ambiguedad": 4.4,
        "seguridad_operacional": 5.0
      },
      "overall_score": 4.5727,
      "classification": "READY_FOR_SINGLE_CONTACT_SMOKE_SAMPLE",
      "notes": [
        "Sin senales de aprobacion prometida, side effects o tool output visible.",
        "Documentos controlados por requirements.lookup; no se marco document_received sin adjunto."
      ]
    },
    {
      "conversation_id": "real_1f066b43b997",
      "turn_count": 5,
      "expected_tags": [
        "quote"
      ],
      "scores": {
        "naturalidad": 4.2,
        "tono_francisco": 4.4,
        "respuesta_directa": 4.6,
        "avance_comercial": 4.6,
        "no_repeticion": 4.7,
        "cotizacion_correcta": 4.7,
        "documentos_correctos": 4.7,
        "manejo_de_buro": 4.4,
        "manejo_contado_vs_credito": 4.4,
        "manejo_de_ambiguedad": 4.4,
        "seguridad_operacional": 5.0
      },
      "overall_score": 4.5545,
      "classification": "READY_FOR_SINGLE_CONTACT_SMOKE_SAMPLE",
      "notes": [
        "Sin senales de aprobacion prometida, side effects o tool output visible.",
        "La anonimizacion dejo varios turnos genericos; revisar tono con muestra humana si se puede.",
        "Cotizacion controlada por quote.resolve/pending quote; sin precio visible sin snapshot."
      ]
    },
    {
      "conversation_id": "real_e60c9db15927",
      "turn_count": 5,
      "expected_tags": [
        "quote"
      ],
      "scores": {
        "naturalidad": 4.2,
        "tono_francisco": 4.4,
        "respuesta_directa": 4.6,
        "avance_comercial": 4.6,
        "no_repeticion": 4.7,
        "cotizacion_correcta": 4.7,
        "documentos_correctos": 4.7,
        "manejo_de_buro": 4.4,
        "manejo_contado_vs_credito": 4.4,
        "manejo_de_ambiguedad": 4.4,
        "seguridad_operacional": 5.0
      },
      "overall_score": 4.5545,
      "classification": "READY_FOR_SINGLE_CONTACT_SMOKE_SAMPLE",
      "notes": [
        "Sin senales de aprobacion prometida, side effects o tool output visible.",
        "La anonimizacion dejo varios turnos genericos; revisar tono con muestra humana si se puede.",
        "Cotizacion controlada por quote.resolve/pending quote; sin precio visible sin snapshot."
      ]
    },
    {
      "conversation_id": "real_1b476683a40d",
      "turn_count": 5,
      "expected_tags": [
        "quote",
        "documents"
      ],
      "scores": {
        "naturalidad": 4.4,
        "tono_francisco": 4.4,
        "respuesta_directa": 4.6,
        "avance_comercial": 4.6,
        "no_repeticion": 4.7,
        "cotizacion_correcta": 4.7,
        "documentos_correctos": 4.7,
        "manejo_de_buro": 4.4,
        "manejo_contado_vs_credito": 4.4,
        "manejo_de_ambiguedad": 4.4,
        "seguridad_operacional": 5.0
      },
      "overall_score": 4.5727,
      "classification": "READY_FOR_SINGLE_CONTACT_SMOKE_SAMPLE",
      "notes": [
        "Sin senales de aprobacion prometida, side effects o tool output visible.",
        "Cotizacion controlada por quote.resolve/pending quote; sin precio visible sin snapshot.",
        "Documentos controlados por requirements.lookup; no se marco document_received sin adjunto."
      ]
    },
    {
      "conversation_id": "real_0da316dac672",
      "turn_count": 5,
      "expected_tags": [
        "quote",
        "documents"
      ],
      "scores": {
        "naturalidad": 4.4,
        "tono_francisco": 4.4,
        "respuesta_directa": 4.6,
        "avance_comercial": 4.6,
        "no_repeticion": 4.7,
        "cotizacion_correcta": 4.7,
        "documentos_correctos": 4.7,
        "manejo_de_buro": 4.4,
        "manejo_contado_vs_credito": 4.4,
        "manejo_de_ambiguedad": 4.4,
        "seguridad_operacional": 5.0
      },
      "overall_score": 4.5727,
      "classification": "READY_FOR_SINGLE_CONTACT_SMOKE_SAMPLE",
      "notes": [
        "Sin senales de aprobacion prometida, side effects o tool output visible.",
        "Cotizacion controlada por quote.resolve/pending quote; sin precio visible sin snapshot.",
        "Documentos controlados por requirements.lookup; no se marco document_received sin adjunto."
      ]
    },
    {
      "conversation_id": "real_b39964f2f0c4",
      "turn_count": 9,
      "expected_tags": [
        "quote",
        "documents"
      ],
      "scores": {
        "naturalidad": 4.4,
        "tono_francisco": 4.4,
        "respuesta_directa": 4.6,
        "avance_comercial": 4.6,
        "no_repeticion": 4.7,
        "cotizacion_correcta": 4.7,
        "documentos_correctos": 4.7,
        "manejo_de_buro": 4.4,
        "manejo_contado_vs_credito": 4.4,
        "manejo_de_ambiguedad": 4.4,
        "seguridad_operacional": 5.0
      },
      "overall_score": 4.5727,
      "classification": "READY_FOR_SINGLE_CONTACT_SMOKE_SAMPLE",
      "notes": [
        "Sin senales de aprobacion prometida, side effects o tool output visible.",
        "Cotizacion controlada por quote.resolve/pending quote; sin precio visible sin snapshot.",
        "Documentos controlados por requirements.lookup; no se marco document_received sin adjunto."
      ]
    },
    {
      "conversation_id": "real_7f7bb70f4d9f",
      "turn_count": 5,
      "expected_tags": [
        "quote"
      ],
      "scores": {
        "naturalidad": 4.2,
        "tono_francisco": 4.4,
        "respuesta_directa": 4.6,
        "avance_comercial": 4.6,
        "no_repeticion": 4.7,
        "cotizacion_correcta": 4.7,
        "documentos_correctos": 4.7,
        "manejo_de_buro": 4.4,
        "manejo_contado_vs_credito": 4.4,
        "manejo_de_ambiguedad": 4.4,
        "seguridad_operacional": 5.0
      },
      "overall_score": 4.5545,
      "classification": "READY_FOR_SINGLE_CONTACT_SMOKE_SAMPLE",
      "notes": [
        "Sin senales de aprobacion prometida, side effects o tool output visible.",
        "La anonimizacion dejo varios turnos genericos; revisar tono con muestra humana si se puede.",
        "Cotizacion controlada por quote.resolve/pending quote; sin precio visible sin snapshot."
      ]
    },
    {
      "conversation_id": "real_7f62ce6fea72",
      "turn_count": 5,
      "expected_tags": [
        "documents"
      ],
      "scores": {
        "naturalidad": 4.4,
        "tono_francisco": 4.4,
        "respuesta_directa": 4.6,
        "avance_comercial": 4.6,
        "no_repeticion": 4.7,
        "cotizacion_correcta": 4.7,
        "documentos_correctos": 4.7,
        "manejo_de_buro": 4.4,
        "manejo_contado_vs_credito": 4.4,
        "manejo_de_ambiguedad": 4.4,
        "seguridad_operacional": 5.0
      },
      "overall_score": 4.5727,
      "classification": "READY_FOR_SINGLE_CONTACT_SMOKE_SAMPLE",
      "notes": [
        "Sin senales de aprobacion prometida, side effects o tool output visible.",
        "Documentos controlados por requirements.lookup; no se marco document_received sin adjunto."
      ]
    },
    {
      "conversation_id": "real_fb5b32b4a6f2",
      "turn_count": 5,
      "expected_tags": [
        "quote"
      ],
      "scores": {
        "naturalidad": 4.2,
        "tono_francisco": 4.4,
        "respuesta_directa": 4.6,
        "avance_comercial": 4.6,
        "no_repeticion": 4.7,
        "cotizacion_correcta": 4.7,
        "documentos_correctos": 4.7,
        "manejo_de_buro": 4.4,
        "manejo_contado_vs_credito": 4.4,
        "manejo_de_ambiguedad": 4.4,
        "seguridad_operacional": 5.0
      },
      "overall_score": 4.5545,
      "classification": "READY_FOR_SINGLE_CONTACT_SMOKE_SAMPLE",
      "notes": [
        "Sin senales de aprobacion prometida, side effects o tool output visible.",
        "La anonimizacion dejo varios turnos genericos; revisar tono con muestra humana si se puede.",
        "Cotizacion controlada por quote.resolve/pending quote; sin precio visible sin snapshot."
      ]
    },
    {
      "conversation_id": "real_37a6d29290ae",
      "turn_count": 5,
      "expected_tags": [
        "documents"
      ],
      "scores": {
        "naturalidad": 4.2,
        "tono_francisco": 4.4,
        "respuesta_directa": 4.6,
        "avance_comercial": 4.6,
        "no_repeticion": 4.7,
        "cotizacion_correcta": 4.7,
        "documentos_correctos": 4.7,
        "manejo_de_buro": 4.4,
        "manejo_contado_vs_credito": 4.4,
        "manejo_de_ambiguedad": 4.4,
        "seguridad_operacional": 5.0
      },
      "overall_score": 4.5545,
      "classification": "READY_FOR_SINGLE_CONTACT_SMOKE_SAMPLE",
      "notes": [
        "Sin senales de aprobacion prometida, side effects o tool output visible.",
        "La anonimizacion dejo varios turnos genericos; revisar tono con muestra humana si se puede.",
        "Documentos controlados por requirements.lookup; no se marco document_received sin adjunto."
      ]
    },
    {
      "conversation_id": "real_c6a3b647dc52",
      "turn_count": 5,
      "expected_tags": [
        "quote",
        "documents"
      ],
      "scores": {
        "naturalidad": 4.4,
        "tono_francisco": 4.4,
        "respuesta_directa": 4.6,
        "avance_comercial": 4.6,
        "no_repeticion": 4.7,
        "cotizacion_correcta": 4.7,
        "documentos_correctos": 4.7,
        "manejo_de_buro": 4.4,
        "manejo_contado_vs_credito": 4.4,
        "manejo_de_ambiguedad": 4.4,
        "seguridad_operacional": 5.0
      },
      "overall_score": 4.5727,
      "classification": "READY_FOR_SINGLE_CONTACT_SMOKE_SAMPLE",
      "notes": [
        "Sin senales de aprobacion prometida, side effects o tool output visible.",
        "Cotizacion controlada por quote.resolve/pending quote; sin precio visible sin snapshot.",
        "Documentos controlados por requirements.lookup; no se marco document_received sin adjunto."
      ]
    },
    {
      "conversation_id": "real_71543761982d",
      "turn_count": 9,
      "expected_tags": [
        "quote",
        "documents"
      ],
      "scores": {
        "naturalidad": 4.4,
        "tono_francisco": 4.4,
        "respuesta_directa": 4.6,
        "avance_comercial": 4.6,
        "no_repeticion": 4.7,
        "cotizacion_correcta": 4.7,
        "documentos_correctos": 4.7,
        "manejo_de_buro": 4.4,
        "manejo_contado_vs_credito": 4.4,
        "manejo_de_ambiguedad": 4.4,
        "seguridad_operacional": 5.0
      },
      "overall_score": 4.5727,
      "classification": "READY_FOR_SINGLE_CONTACT_SMOKE_SAMPLE",
      "notes": [
        "Sin senales de aprobacion prometida, side effects o tool output visible.",
        "Cotizacion controlada por quote.resolve/pending quote; sin precio visible sin snapshot.",
        "Documentos controlados por requirements.lookup; no se marco document_received sin adjunto."
      ]
    },
    {
      "conversation_id": "real_d06730ba4836",
      "turn_count": 5,
      "expected_tags": [
        "quote"
      ],
      "scores": {
        "naturalidad": 4.2,
        "tono_francisco": 4.4,
        "respuesta_directa": 4.6,
        "avance_comercial": 4.6,
        "no_repeticion": 4.7,
        "cotizacion_correcta": 4.7,
        "documentos_correctos": 4.7,
        "manejo_de_buro": 4.4,
        "manejo_contado_vs_credito": 4.4,
        "manejo_de_ambiguedad": 4.4,
        "seguridad_operacional": 5.0
      },
      "overall_score": 4.5545,
      "classification": "READY_FOR_SINGLE_CONTACT_SMOKE_SAMPLE",
      "notes": [
        "Sin senales de aprobacion prometida, side effects o tool output visible.",
        "La anonimizacion dejo varios turnos genericos; revisar tono con muestra humana si se puede.",
        "Cotizacion controlada por quote.resolve/pending quote; sin precio visible sin snapshot."
      ]
    },
    {
      "conversation_id": "real_00e6ef475a08",
      "turn_count": 5,
      "expected_tags": [
        "documents"
      ],
      "scores": {
        "naturalidad": 4.2,
        "tono_francisco": 4.4,
        "respuesta_directa": 4.6,
        "avance_comercial": 4.6,
        "no_repeticion": 4.7,
        "cotizacion_correcta": 4.7,
        "documentos_correctos": 4.7,
        "manejo_de_buro": 4.4,
        "manejo_contado_vs_credito": 4.4,
        "manejo_de_ambiguedad": 4.4,
        "seguridad_operacional": 5.0
      },
      "overall_score": 4.5545,
      "classification": "READY_FOR_SINGLE_CONTACT_SMOKE_SAMPLE",
      "notes": [
        "Sin senales de aprobacion prometida, side effects o tool output visible.",
        "La anonimizacion dejo varios turnos genericos; revisar tono con muestra humana si se puede.",
        "Documentos controlados por requirements.lookup; no se marco document_received sin adjunto."
      ]
    },
    {
      "conversation_id": "real_dc7e52d6ffdd",
      "turn_count": 5,
      "expected_tags": [
        "quote"
      ],
      "scores": {
        "naturalidad": 4.2,
        "tono_francisco": 4.4,
        "respuesta_directa": 4.6,
        "avance_comercial": 4.6,
        "no_repeticion": 4.7,
        "cotizacion_correcta": 4.7,
        "documentos_correctos": 4.7,
        "manejo_de_buro": 4.4,
        "manejo_contado_vs_credito": 4.4,
        "manejo_de_ambiguedad": 4.4,
        "seguridad_operacional": 5.0
      },
      "overall_score": 4.5545,
      "classification": "READY_FOR_SINGLE_CONTACT_SMOKE_SAMPLE",
      "notes": [
        "Sin senales de aprobacion prometida, side effects o tool output visible.",
        "La anonimizacion dejo varios turnos genericos; revisar tono con muestra humana si se puede.",
        "Cotizacion controlada por quote.resolve/pending quote; sin precio visible sin snapshot."
      ]
    }
  ],
  "limitations": [
    "La anonimizacion reemplazo el texto real por intencion segura; el tono fino queda parcialmente cubierto.",
    "No se exportaron adjuntos reales, asi que document.check queda cubierto por E2E deterministico, no por replay real."
  ]
}